functions3/__init__.py
functions3/transformations.py
functions3-0.1.3.dist-info/METADATA
functions3-0.1.3.dist-info/WHEEL
functions3-0.1.3.dist-info/RECORD
