Metadata-Version: 2.1
Name: functions3
Version: 0.1.3
Summary: 3 functions for for sprint 2.1 module
Author: zivilevs
Author-email: zivileval@yahoo.com
Requires-Python: >=3.9,<4.0
Classifier: Programming Language :: Python :: 3
Classifier: Programming Language :: Python :: 3.9
Classifier: Programming Language :: Python :: 3.10
Classifier: Programming Language :: Python :: 3.11
Requires-Dist: numpy (>=1.25.2,<2.0.0)
